Metadata-Version: 2.1
Name: imzmqx
Version: 1.1.2
Summary: Transporting OpenCV images via ZMQ - enhanced.
Home-page: https://github.com/minlaxz/imzmqx
Author: Jeff Bass, Min Latt
Author-email: jeff@yin-yang-ranch.com, minminlaxz@gmail.com
License: MIT
Keywords: opencv-python,pyzmq,raspberrypi,imzmqx
Platform: UNKNOWN
Classifier: Development Status :: 5 - Production/Stable
Classifier: Intended Audience :: Developers
Classifier: Natural Language :: English
Classifier: License :: OSI Approved :: MIT License
Classifier: Programming Language :: Python
Classifier: Programming Language :: Python :: 3
Classifier: Programming Language :: Python :: 3.5
Classifier: Programming Language :: Python :: 3.6
Classifier: Programming Language :: Python :: 3.7
Classifier: Programming Language :: Python :: 3.8
Classifier: Programming Language :: Python :: Implementation :: CPython
Requires-Python: >=3.5
